sqladmin_whiteleads/__init__.py
sqladmin_whiteleads/_menu.py
sqladmin_whiteleads/_queries.py
sqladmin_whiteleads/_types.py
sqladmin_whiteleads/_validators.py
sqladmin_whiteleads/ajax.py
sqladmin_whiteleads/application.py
sqladmin_whiteleads/authentication.py
sqladmin_whiteleads/exceptions.py
sqladmin_whiteleads/fields.py
sqladmin_whiteleads/filters.py
sqladmin_whiteleads/formatters.py
sqladmin_whiteleads/forms.py
sqladmin_whiteleads/helpers.py
sqladmin_whiteleads/models.py
sqladmin_whiteleads/pagination.py
sqladmin_whiteleads/py.typed
sqladmin_whiteleads/templating.py
sqladmin_whiteleads/widgets.py
sqladmin_whiteleads/statics/css/flatpickr.min.css
sqladmin_whiteleads/statics/css/fontawesome.min.css
sqladmin_whiteleads/statics/css/main.css
sqladmin_whiteleads/statics/css/select2.min.css
sqladmin_whiteleads/statics/css/tabler-icons.min.css
sqladmin_whiteleads/statics/css/tabler-icons.min.css.map
sqladmin_whiteleads/statics/css/tabler.min.css
sqladmin_whiteleads/statics/js/bootstrap.min.js
sqladmin_whiteleads/statics/js/flatpickr.min.js
sqladmin_whiteleads/statics/js/jquery.min.js
sqladmin_whiteleads/statics/js/main.js
sqladmin_whiteleads/statics/js/popper.min.js
sqladmin_whiteleads/statics/js/select2.full.min.js
sqladmin_whiteleads/statics/js/tabler.min.js
sqladmin_whiteleads/statics/webfonts/fa-brands-400.woff2
sqladmin_whiteleads/statics/webfonts/fa-regular-400.woff2
sqladmin_whiteleads/statics/webfonts/fa-solid-900.woff2
sqladmin_whiteleads/statics/webfonts/tabler-icons.woff2
sqladmin_whiteleads/templates/sqladmin/_macros.html
sqladmin_whiteleads/templates/sqladmin/base.html
sqladmin_whiteleads/templates/sqladmin/create.html
sqladmin_whiteleads/templates/sqladmin/details.html
sqladmin_whiteleads/templates/sqladmin/edit.html
sqladmin_whiteleads/templates/sqladmin/error.html
sqladmin_whiteleads/templates/sqladmin/index.html
sqladmin_whiteleads/templates/sqladmin/layout.html
sqladmin_whiteleads/templates/sqladmin/list.html
sqladmin_whiteleads-1.4.0.9.dist-info/licenses/LICENSE.md
sqladmin_whiteleads-1.4.0.9.dist-info/METADATA
sqladmin_whiteleads-1.4.0.9.dist-info/WHEEL
sqladmin_whiteleads-1.4.0.9.dist-info/top_level.txt
sqladmin_whiteleads-1.4.0.9.dist-info/RECORD
