Metadata-Version: 2.4
Name: sqladmin_whiteleads
Version: 1.4.0.9
Summary: Fork of SQLAdmin with custom modifications
Author-email: Olga Kozynkina <ko3.olga@gmail.com>
License: MIT
Project-URL: Homepage, https://github.com/olga3ok/sqladmin-whiteleads
Classifier: Development Status :: 3 - Alpha
Classifier: Intended Audience :: Developers
Classifier: Programming Language :: Python :: 3
Requires-Python: >=3.7
License-File: LICENSE.md
Requires-Dist: starlette
Requires-Dist: sqlalchemy>=1.4
Requires-Dist: wtforms<3.2,>=3.1
Requires-Dist: jinja2
Requires-Dist: python-multipart
Dynamic: license-file
